gcdt_say_hello
